jetstream/__init__.py
jetstream/cli.py
jetstream/publisher.py
jetstream/template.py
jetstream/testing.py
jetstream-0.1.0.dist-info/DESCRIPTION.rst
jetstream-0.1.0.dist-info/METADATA
jetstream-0.1.0.dist-info/RECORD
jetstream-0.1.0.dist-info/WHEEL
jetstream-0.1.0.dist-info/entry_points.txt
jetstream-0.1.0.dist-info/metadata.json
jetstream-0.1.0.dist-info/top_level.txt
test_templates/__init__.py
test_templates/ec2_instance.py
test_templates/s3_bucket.py
